greatday/__init__.py
greatday/__main__.py
greatday/common.py
greatday/config.py
greatday/dates.py
greatday/db.py
greatday/models.py
greatday/py.typed
greatday/repo.py
greatday/runners.py
greatday/session.py
greatday/spells.py
greatday/tag.py
greatday/todo.py
greatday/tui.py
greatday/types.py
greatday-1.1.0.dist-info/METADATA
greatday-1.1.0.dist-info/WHEEL
greatday-1.1.0.dist-info/entry_points.txt
greatday-1.1.0.dist-info/top_level.txt
greatday-1.1.0.dist-info/RECORD
