Metadata-Version: 2.1
Name: greatday
Version: 1.1.0
Summary: Don't have a good day. Have a great day.
Home-page: https://github.com/bbugyi200/greatday
Author: Bryan M Bugyi
Author-email: bryanbugyi34@gmail.com
License: MIT license
Classifier: Development Status :: 3 - Alpha
Classifier: Intended Audience :: Developers
Classifier: License :: OSI Approved :: MIT License
Classifier: Natural Language :: English
Classifier: Programming Language :: Python :: 3
Classifier: Programming Language :: Python :: 3.8
Classifier: Programming Language :: Python :: 3.9
Classifier: Programming Language :: Python :: 3.10
Requires-Python: >=3.8
Requires-Dist: bolton-clack (~=0.3.3)
Requires-Dist: bolton-eris (~=0.2.3)
Requires-Dist: bolton-logrus (~=0.1.0)
Requires-Dist: bolton-metaman (~=0.1.2)
Requires-Dist: bolton-typist (~=0.2.0)
Requires-Dist: magodo (~=1.1)
Requires-Dist: potoroo (~=0.4.1)
Requires-Dist: python-dateutil (~=2.8)
Requires-Dist: sqlmodel (~=0.0.6)
Requires-Dist: textual[dev] (~=0.11)
Requires-Dist: vimala (~=0.1.2)
Requires-Dist: sqlalchemy (==1.4.35)
